COPYING
LICENSE
README.rst
chwloc.pyx
linuxsched.pyx
setup.py
doc/guide.html
doc/guide.md
doc/hwloc-hello.py
hwloc/__init__.py
hwloc/hwloc.py
python3_hwloc.egg-info/PKG-INFO
python3_hwloc.egg-info/SOURCES.txt
python3_hwloc.egg-info/dependency_links.txt
python3_hwloc.egg-info/requires.txt
python3_hwloc.egg-info/top_level.txt