Metadata-Version: 1.1
Name: python3-hwloc
Version: 2.3.6.0.1.11.5
Summary: python bindings for hwloc
Home-page: https://gitlab.com/guystreeter/python-hwloc
Author: Guy Streeter <guy.streeter@gmail.com>
Author-email: guy.streeter@gmail.com
License: GPLv2+
Platform: UNKNOWN
Classifier: Environment :: Other Environment
Classifier: Development Status :: 5 - Production/Stable
Classifier: Intended Audience :: Developers
Classifier: License :: OSI Approved :: GNU General Public License v2 or later (GPLv2+)
Classifier: Operating System :: POSIX :: Linux
Classifier: Programming Language :: Python
Classifier: Topic :: System :: Systems Administration
